{
    "addons": {
        "__newtabpage@vitaliy.com": {
            "updates": [
                {
                    "version": "2024.5.10",
                    "update_link": "https://vitaliyvstyle.github.io/WebExtExperiments/new_tab_page.2024.5.10.xpi",
                    "applications": {
                        "gecko": {
                            "strict_min_version": "117.0"
                        }
                    }
                }
            ]
        },
        "add_toolbar_buttons@vitaliy.com": {
            "updates": [
                {
                    "version": "2024.5.23",
                    "update_link": "https://vitaliyvstyle.github.io/WebExtExperiments/add_toolbar_buttons.2024.5.23.xpi",
                    "applications": {
                        "gecko": {
                            "strict_min_version": "117.0"
                        }
                    }
                }
            ]
        },
        "async_run_applications@vitaliy.com": {
            "updates": [
                {
                    "version": "2024.5.28",
                    "update_link": "https://vitaliyvstyle.github.io/WebExtExperiments/async_run_applications.2024.5.28.xpi",
                    "applications": {
                        "gecko": {
                            "strict_min_version": "117.0"
                        }
                    }
                }
            ]
        },
        "tabs_focus@vitaliy.com": {
            "updates": [
                {
                    "version": "2024.4.20",
                    "update_link": "https://vitaliyvstyle.github.io/WebExtExperiments/tabs_focus.2024.4.20.xpi",
                    "applications": {
                        "gecko": {
                            "strict_min_version": "117.0"
                        }
                    }
                }
            ]
        },
        "long_left_click@vitaliy.com": {
            "updates": [
                {
                    "version": "2024.4.28",
                    "update_link": "https://vitaliyvstyle.github.io/WebExtExperiments/long_left_click.2024.4.28.xpi",
                    "applications": {
                        "gecko": {
                            "strict_min_version": "117.0"
                        }
                    }
                }
            ]
        },
        "__dark_warm_rose_theme_exp@vitaliy.com": {
            "updates": [
                {
                    "version": "2024.4.20",
                    "update_link": "https://vitaliyvstyle.github.io/WebExtExperiments/dark_warm_rose_theme_exp.2024.4.20.xpi",
                    "applications": {
                        "gecko": {
                            "strict_min_version": "117.0"
                        }
                    }
                }
            ]
        },
        "__dark_cold_violet_theme_exp@vitaliy.com": {
            "updates": [
                {
                    "version": "2024.4.20",
                    "update_link": "https://vitaliyvstyle.github.io/WebExtExperiments/dark_cold_violet_theme_exp.2024.4.20.xpi",
                    "applications": {
                        "gecko": {
                            "strict_min_version": "117.0"
                        }
                    }
                }
            ]
        }
    }
}
